[
  {
    "id": 301,
    "title": "Drehmomentschlüssel 1/2\"",
    "slug": "drehmomentschluessel-1-2",
    "price": 49.99,
    "description": "Präziser Drehmomentschlüssel mit klickfunktion, 10–80 Nm.",
    "category": { "id": 3, "name": "Werkzeuge", "slug": "werkzeuge", "image": "https://placehold.co/200x150?text=Werkzeuge" },
    "images": ["https://placehold.co/800x600?text=Schluessel"],
    "subcategoryId": 5
  },
  {
    "id": 302,
    "title": "Satz Steckschlüssel 1/4\" (12-teilig)",
    "slug": "steckschluessel-satz-12",
    "price": 29.95,
    "description": "Robuste Steckschlüssel für Schraubarbeiten am Fahrzeug.",
    "category": { "id": 3, "name": "Werkzeuge", "slug": "werkzeuge", "image": "https://placehold.co/200x150?text=Werkzeuge" },
    "images": ["https://placehold.co/800x600?text=Steckschluessel"],
    "subcategoryId": 5
  }
]
